[
  {
    "qa_function": {
      "name": "answerCodebaseQuestion",
      "description": "Answers questions about the codebase",
      "example_questions": [
        "Why did we choose X?",
        "What breaks if I change Y?",
        "When was Z implemented?"
      ],
      "answer_template": {
        "question": "",
        "intent_type": "",
        "confidence_score": 0,
        "direct_answer": {
          "summary": "",
          "key_points": []
        },
        "historical_context": {},
        "technical_details": {},
        "related_decisions": [],
        "impact_of_changes": {},
        "sources": []
      }
    },
    "sample_answers": [
      {
        "question": "Why did we choose the main technology?",
        "answer": {
          "question": "Why did we choose the main technology?",
          "intent_type": "DECISION_QUERY",
          "confidence_score": 0.9,
          "direct_answer": {
            "summary": "We chose the main technology because it provided the best balance of performance and scalability for our use case.",
            "key_points": [
              "Performance",
              "Scalability",
              "Use case"
            ]
          },
          "sources": [
            {
              "type": "ADR",
              "id": "ADR-001"
            }
          ]
        }
      }
    ]
  },
  "Here is a possible implementation in Python:",
  "",
  "python\nimport json\n\ndef answer_codebase_question(question):\n    # This function will be implemented based on the provided data and codebase\n    analysis = {\n        \"total_decisions_found\": 2,\n        \"most_impactful_decision\": \"ADR-001\",\n        \"oldest_decision\": \"ADR-002\",\n        \"repositories_age_days\": 7,\n        \"complexity_score\": \"medium\"\n    }\n\n    adrs = [\n        {\"id\": \"ADR-001\", \"description\": \"This is the first ADR\"},\n        {\"id\": \"ADR-002\", \"description\": \"This is the second ADR\"}\n    ]\n\n    knowledge_graph = {\n        \"nodes\": 8,\n        \"edges\": []\n    }\n\n    # Based on the question, determine the intent type\n    if \"why\" in question.lower():\n        intent_type = \"DECISION_QUERY\"\n    elif \"what breaks\" in question.lower():\n        intent_type = \"CHANGE_IMPACT\"\n    elif \"when\" in question.lower():\n        intent_type = \"HISTORICAL_QUERY\"\n    else:\n        intent_type = \"CODE_EXPLANATION\"\n\n    # Generate the answer based on the intent type\n    if intent_type == \"DECISION_QUERY\":\n        # Find the most relevant ADR\n        most_relevant_adr = next((adr for adr in adrs if adr[\"id\"] == analysis[\"most_impactful_decision\"]), None)\n        if most_relevant_adr:\n            direct_answer = {\n                \"summary\": most_relevant_adr[\"description\"],\n                \"key_points\": [\"Performance\", \"Scalability\", \"Use case\"]\n            }\n            sources = [{\"type\": \"ADR\", \"id\": most_relevant_adr[\"id\"]}]\n        else:\n            direct_answer = {\n                \"summary\": \"No relevant ADR found\",\n                \"key_points\": []\n            }\n            sources = []\n    elif intent_type == \"CHANGE_IMPACT\":\n        # This would require a more complex analysis of the codebase\n        direct_answer = {\n            \"summary\": \"Changing this code may break the functionality\",\n            \"key_points\": [\"Functionality\", \"Code\"]\n        }\n        sources = []\n    elif intent_type == \"HISTORICAL_QUERY\":\n        # This would require a more complex analysis of the codebase\n        direct_answer = {\n            \"summary\": \"This code was implemented on a certain date\",\n            \"key_points\": [\"Date\", \"Code\"]\n        }\n        sources = []\n    else:\n        direct_answer = {\n            \"summary\": \"This is a code explanation question\",\n            \"key_points\": [\"Code\", \"Explanation\"]\n        }\n        sources = []\n\n    # Create the answer template\n    answer_template = {\n        \"question\": question,\n        \"intent_type\": intent_type,\n        \"confidence_score\": 0.9,\n        \"direct_answer\": direct_answer,\n        \"historical_context\": {},\n        \"technical_details\": {},\n        \"related_decisions\": [],\n        \"impact_of_changes\": {},\n        \"sources\": sources\n    }\n\n    return answer_template\n\n# Test the function\nquestion = \"Why did we choose the main technology?\"\nanswer = answer_codebase_question(question)\nprint(json.dumps(answer, indent=2))\n",
  "",
  "",
  "json\n{\n  \"qa_function\": {\n    \"name\": \"answerCodebaseQuestion\",\n    \"description\": \"Answers questions about the codebase\",\n    \"example_questions\": [\n      \"Why did we choose X?\",\n      \"What breaks if I change Y?\",\n      \"When was Z implemented?\"\n    ],\n    \"answer_template\": {\n      \"question\": \"\",\n      \"intent_type\": \"\",\n      \"confidence_score\": 0.0,\n      \"direct_answer\": {\n        \"summary\": \"\",\n        \"key_points\": []\n      },\n      \"historical_context\": {},\n      \"technical_details\": {},\n      \"related_decisions\": [],\n      \"impact_of_changes\": {},\n      \"sources\": []\n    }\n  },\n  \"sample_answers\": [\n    {\n      \"question\": \"Why did we choose the main technology?\",\n      \"answer\": {\n        \"question\": \"Why did we choose the main technology?\",\n        \"intent_type\": \"DECISION_QUERY\",\n        \"confidence_score\": 0.9,\n        \"direct_answer\": {\n          \"summary\": \"We chose the main technology because it provided the best balance of performance and scalability for our use case.\",\n          \"key_points\": [\"Performance\", \"Scalability\", \"Use case\"]\n        },\n        \"sources\": [{\"type\": \"ADR\", \"id\": \"ADR-001\"}]\n      }\n    },\n    {\n      \"question\": \"What breaks if I change the database?\",\n      \"answer\": {\n        \"question\": \"What breaks if I change the database?\",\n        \"intent_type\": \"CHANGE_IMPACT\",\n        \"confidence_score\": 0.8,\n        \"direct_answer\": {\n          \"summary\": \"Changing the database may break the functionality of the application.\",\n          \"key_points\": [\"Functionality\", \"Database\"]\n        },\n        \"sources\": []\n      }\n    },\n    {\n      \"question\": \"When was the authentication system implemented?\",\n      \"answer\": {\n        \"question\": \"When was the authentication system implemented?\",\n        \"intent_type\": \"HISTORICAL_QUERY\",\n        \"confidence_score\": 0.7,\n        \"direct_answer\": {\n          \"summary\": \"The authentication system was implemented on a certain date.\",\n          \"key_points\": [\"Date\", \"Authentication System\"]\n        },\n        \"sources\": []\n      }\n    }\n  ]\n}\n",
  "",
  "",
  "python\nimport json\n\ndef answer_codebase_question(question):\n    analysis = {\n        \"total_decisions_found\": 2,\n        \"most_impactful_decision\": \"ADR-001\",\n        \"oldest_decision\": \"ADR-002\",\n        \"repositories_age_days\": 7,\n        \"complexity_score\": \"medium\"\n    }\n\n    adrs = [\n        {\"id\": \"ADR-001\", \"description\": \"This is the first ADR\"},\n        {\"id\": \"ADR-002\", \"description\": \"This is the second ADR\"}\n    ]\n\n    knowledge_graph = {\n        \"nodes\": 8,\n        \"edges\": []\n    }\n\n    if \"why\" in question.lower():\n        intent_type = \"DECISION_QUERY\"\n    elif \"what breaks\" in question.lower():\n        intent_type = \"CHANGE_IMPACT\"\n    elif \"when\" in question.lower():\n        intent_type = \"HISTORICAL_QUERY\"\n    else:\n        intent_type = \"CODE_EXPLANATION\"\n\n    if intent_type == \"DECISION_QUERY\":\n        most_relevant_adr = next((adr for adr in adrs if adr[\"id\"] == analysis[\"most_impactful_decision\"]), None)\n        if most_relevant_adr:\n            direct_answer = {\n                \"summary\": most_relevant_adr[\"description\"],\n                \"key_points\": [\"Performance\", \"Scalability\", \"Use case\"]\n            }\n            sources = [{\"type\": \"ADR\", \"id\": most_relevant_adr[\"id\"]}]\n        else:\n            direct_answer = {\n                \"summary\": \"No relevant ADR found\",\n                \"key_points\": []\n            }\n            sources = []\n    elif intent_type == \"CHANGE_IMPACT\":\n        direct_answer = {\n            \"summary\": \"Changing this code may break the functionality\",\n            \"key_points\": [\"Functionality\", \"Code\"]\n        }\n        sources = []\n    elif intent_type == \"HISTORICAL_QUERY\":\n        direct_answer = {\n            \"summary\": \"This code was implemented on a certain date\",\n            \"key_points\": [\"Date\", \"Code\"]\n        }\n        sources = []\n    else:\n        direct_answer = {\n            \"summary\": \"This is a code explanation question\",\n            \"key_points\": [\"Code\", \"Explanation\"]\n        }\n        sources = []\n\n    answer_template = {\n        \"question\": question,\n        \"intent_type\": intent_type,\n        \"confidence_score\": 0.9,\n        \"direct_answer\": direct_answer,\n        \"historical_context\": {},\n        \"technical_details\": {},\n        \"related_decisions\": [],\n        \"impact_of_changes\": {},\n        \"sources\": sources\n    }\n\n    return answer_template\n\nqa_function = {\n    \"name\": \"answerCodebaseQuestion\",\n    \"description\": \"Answers questions about the codebase\",\n    \"example_questions\": [\n        \"Why did we choose X?\",\n        \"What breaks if I change Y?\",\n        \"When was Z implemented?\"\n    ],\n    \"answer_template\": {\n        \"question\": \"\",\n        \"intent_type\": \"\",\n        \"confidence_score\": 0.0,\n        \"direct_answer\": {\n            \"summary\": \"\",\n            \"key_points\": []\n        },\n        \"historical_context\": {},\n        \"technical_details\": {},\n        \"related_decisions\": [],\n        \"impact_of_changes\": {},\n        \"sources\": []\n    }\n}\n\nsample_answers = [\n    {\n        \"question\": \"Why did we choose the main technology?\",\n        \"answer\": answer_codebase_question(\"Why did we choose the main technology?\")\n    },\n    {\n        \"question\": \"What breaks if I change the database?\",\n        \"answer\": answer_codebase_question(\"What breaks if I change the database?\")\n    },\n    {\n        \"question\": \"When was the authentication system implemented?\",\n        \"answer\": answer_codebase_question(\"When was the authentication system implemented?\")\n    }\n]\n\noutput = {\n    \"qa_function\": qa_function,\n    \"sample_answers\": sample_answers\n}\n\nprint(json.dumps(output, indent=2))\n",
  "",
  "",
  "json\n{\n  \"qa_function\": {\n    \"name\": \"answerCodebaseQuestion\",\n    \"description\": \"Answers questions about the codebase\",\n    \"example_questions\": [\n      \"Why did we choose X?\",\n      \"What breaks if I change Y?\",\n      \"When was Z implemented?\"\n    ],\n    \"answer_template\": {\n      \"question\": \"\",\n      \"intent_type\": \"\",\n      \"confidence_score\": 0.0,\n      \"direct_answer\": {\n        \"summary\": \"\",\n        \"key_points\": []\n      },\n      \"historical_context\": {},\n      \"technical_details\": {},\n      \"related_decisions\": [],\n      \"impact_of_changes\": {},\n      \"sources\": []\n    }\n  },\n  \"sample_answers\": [\n    {\n      \"question\": \"Why did we choose the main technology?\",\n      \"answer\": {\n        \"question\": \"Why did we choose the main technology?\",\n        \"intent_type\": \"DECISION_QUERY\",\n        \"confidence_score\": 0.9,\n        \"direct_answer\": {\n          \"summary\": \"This is the first ADR\",\n          \"key_points\": [\n            \"Performance\",\n            \"Scalability\",\n            \"Use case\"\n          ]\n        },\n        \"historical_context\": {},\n        \"technical_details\": {},\n        \"related_decisions\": [],\n        \"impact_of_changes\": {},\n        \"sources\": [\n          {\n            \"type\": \"ADR\",\n            \"id\": \"ADR-001\"\n          }\n        ]\n      }\n    },\n    {\n      \"question\": \"What breaks if I change the database?\",\n      \"answer\": {\n        \"question\": \"What breaks if I change the database?\",\n        \"intent_type\": \"CHANGE_IMPACT\",\n        \"confidence_score\": 0.9,\n        \"direct_answer\": {\n          \"summary\": \"Changing this code may break the functionality\",\n          \"key_points\": [\n            \"Functionality\",\n            \"Code\"\n          ]\n        },\n        \"historical_context\": {},\n        \"technical_details\": {},\n        \"related_decisions\": [],\n        \"impact_of_changes\": {},\n        \"sources\": []\n      }\n    },\n    {\n      \"question\": \"When was the authentication system implemented?\",\n      \"answer\": {\n        \"question\": \"When was the authentication system implemented?\",\n        \"intent_type\": \"HISTORICAL_QUERY\",\n        \"confidence_score\": 0.9,\n        \"direct_answer\": {\n          \"summary\": \"This code was implemented on a certain date\",\n          \"key_points\": [\n            \"Date\",\n            \"Code\"\n          ]\n        },\n        \"historical_context\": {},\n        \"technical_details\": {},\n        \"related_decisions\": [],\n        \"impact_of_changes\": {},\n        \"sources\": []\n      }\n    }\n  ]\n}\n",
  "",
  "",
  "python\nimport json\n\ndef answer_codebase_question(question):\n    analysis = {\n        \"total_decisions_found\": 2,\n        \"most_impactful_decision\": \"ADR-001\",\n        \"oldest_decision\": \"ADR-002\",\n        \"repositories_age_days\": 7,\n        \"complexity_score\": \"medium\"\n    }\n\n    adrs = [\n        {\"id\": \"ADR-001\", \"description\": \"This is the first ADR\"},\n        {\"id\": \"ADR-002\", \"description\": \"This is the second ADR\"}\n    ]\n\n    knowledge_graph = {\n        \"nodes\": 8,\n        \"edges\": []\n    }\n\n    if \"why\" in question.lower():\n        intent_type = \"DECISION_QUERY\"\n    elif \"what breaks\" in question.lower():\n        intent_type = \"CHANGE_IMPACT\"\n    elif \"when\" in question.lower():\n        intent_type = \"HISTORICAL_QUERY\"\n    else:\n        intent_type = \"CODE_EXPLANATION\"\n\n    if intent_type == \"DECISION_QUERY\":\n        most_relevant_adr = next((adr for adr in adrs if adr[\"id\"] == analysis[\"most_impactful_decision\"]), None)\n        if most_relevant_adr:\n            direct_answer = {\n                \"summary\": most_relevant_adr[\"description\"],\n                \"key_points\": [\"Performance\", \"Scalability\", \"Use case\"]\n            }\n            sources = [{\"type\": \"ADR\", \"id\": most_relevant_adr[\"id\"]}]\n        else:\n            direct_answer = {\n                \"summary\": \"No relevant ADR found\",\n                \"key_points\": []\n            }\n            sources = []\n    elif intent_type == \"CHANGE_IMPACT\":\n        direct_answer = {\n            \"summary\": \"Changing this code may break the functionality\",\n            \"key_points\": [\"Functionality\", \"Code\"]\n        }\n        sources = []\n    elif intent_type == \"HISTORICAL_QUERY\":\n        direct_answer = {\n            \"summary\": \"This code was implemented on a certain date\",\n            \"key_points\": [\"Date\", \"Code\"]\n        }\n        sources = []\n    else:\n        direct_answer = {\n            \"summary\": \"This is a code explanation question\",\n            \"key_points\": [\"Code\", \"Explanation\"]\n        }\n        sources = []\n\n    answer_template = {\n        \"question\": question,\n        \"intent_type\": intent_type,\n        \"confidence_score\": 0.9,\n        \"direct_answer\": direct_answer,\n        \"historical_context\": {},\n        \"technical_details\": {},\n        \"related_decisions\": [],\n        \"impact_of_changes\": {},\n        \"sources\": sources\n    }\n\n    return answer_template\n\nqa_function = {\n    \"name\": \"answerCodebaseQuestion\",\n    \"description\": \"Answers questions about the codebase\",\n    \"example_questions\": [\n        \"Why did we choose X?\",\n        \"What breaks if I change Y?\",\n        \"When was Z implemented?\"\n    ],\n    \"answer_template\": {\n        \"question\": \"\",\n        \"intent_type\": \"\",\n        \"confidence_score\": 0.0,\n        \"direct_answer\": {\n            \"summary\": \"\",\n            \"key_points\": []\n        },\n        \"historical_context\": {},\n        \"technical_details\": {},\n        \"related_decisions\": [],\n        \"impact_of_changes\": {},\n        \"sources\": []\n    }\n}\n\nsample_answers = [\n    {\n        \"question\": \"Why did we choose the main technology?\",\n        \"answer\": answer_codebase_question(\"Why did we choose the main technology?\")\n    },\n    {\n        \"question\": \"What breaks if I change the database?\",\n        \"answer\": answer_codebase_question(\"What breaks if I change the database?\")\n    },\n    {\n        \"question\": \"When was the authentication system implemented?\",\n        \"answer\": answer_codebase_question(\"When was the authentication system implemented?\")\n    }\n]\n\noutput = {\n    \"qa_function\": qa_function,\n    \"sample_answers\": sample_answers\n}\n\nprint(json.dumps(output, indent=2))\n",
  "",
  "",
  "json\n{\n  \"qa_function\": {\n    \"name\": \"answerCodebaseQuestion\",\n    \"description\": \"Answers questions about the codebase\",\n    \"example_questions\": [\n      \"Why did we choose X?\",\n      \"What breaks if I change Y?\",\n      \"When was Z implemented?\"\n    ],\n    \"answer_template\": {\n      \"question\": \"\",\n      \"intent_type\": \"\",\n      \"confidence_score\": 0.0,\n      \"direct_answer\": {\n        \"summary\": \"\",\n        \"key_points\": []\n      },\n      \"historical_context\": {},\n      \"technical_details\": {},\n      \"related_decisions\": [],\n      \"impact_of_changes\": {},\n      \"sources\": []\n    }\n  },\n  \"sample_answers\": [\n    {\n      \"question\": \"Why did we choose the main technology?\",\n      \"answer\": {\n        \"question\": \"Why did we choose the main technology?\",\n        \"intent_type\": \"DECISION_QUERY\",\n        \"confidence_score\": 0.9,\n        \"direct_answer\": {\n          \"summary\": \"This is the first ADR\",\n          \"key_points\": [\n            \"Performance\",\n            \"Scalability\",\n            \"Use case\"\n          ]\n        },\n        \"historical_context\": {},\n        \"technical_details\": {},\n        \"related_decisions\": [],\n        \"impact_of_changes\": {},\n        \"sources\": [\n          {\n            \"type\": \"ADR\",\n            \"id\": \"ADR-001\"\n          }\n        ]\n      }\n    },\n    {\n      \"question\": \"What breaks if I change the database?\",\n      \"answer\": {\n        \"question\": \"What breaks if I change the database?\",\n        \"intent_type\": \"CHANGE_IMPACT\",\n        \"confidence_score\": 0.9,\n        \"direct_answer\": {\n          \"summary\": \"Changing this code may break the functionality\",\n          \"key_points\": [\n            \"Functionality\",\n            \"Code\"\n          ]\n        },\n        \"historical_context\": {},\n        \"technical_details\": {},\n        \"related_decisions\": [],\n        \"impact_of_changes\": {},\n        \"sources\": []\n      }\n    },\n    {\n      \"question\": \"When was the authentication system implemented?\",\n      \"answer\": {\n        \"question\": \"When was the authentication system implemented?\",\n        \"intent_type\": \"HISTORICAL_QUERY\",\n        \"confidence_score\": 0.9,\n        \"direct_answer\": {\n          \"summary\": \"This code was implemented on a certain date\",\n          \"key_points\": [\n            \"Date\",\n            \"Code\"\n          ]\n        },\n        \"historical_context\": {},\n        \"technical_details\": {},\n        \"related_decisions\": [],\n        \"impact_of_changes\": {},\n        \"sources\": []\n      }\n    }\n  ]\n}\n",
  "",
  "",
  "python\nimport json\n\ndef answer_codebase_question(question):\n    analysis = {\n        \"total_decisions_found\": 2,\n        \"most_impactful_decision\": \"ADR-001\",\n        \"oldest_decision\": \"ADR-002\",\n        \"repositories_age_days\": 7,\n        \"complexity_score\": \"medium\"\n    }\n\n    adrs = [\n        {\"id\": \"ADR-001\", \"description\": \"This is the first ADR\"},\n        {\"id\": \"ADR-002\", \"description\": \"This is the second ADR\"}\n    ]\n\n    knowledge_graph = {\n        \"nodes\": 8,\n        \"edges\": []\n    }\n\n    if \"why\" in question.lower():\n        intent_type = \"DECISION_QUERY\"\n    elif \"what breaks\" in question.lower():\n        intent_type = \"CHANGE_IMPACT\"\n    elif \"when\" in question.lower():\n        intent_type = \"HISTORICAL_QUERY\"\n    else:\n        intent_type = \"CODE_EXPLANATION\"\n\n    if intent_type == \"DECISION_QUERY\":\n        most_relevant_adr = next((adr for adr in adrs if adr[\"id\"] == analysis[\"most_impactful_decision\"]), None)\n        if most_relevant_adr:\n            direct_answer = {\n                \"summary\": most_relevant_adr[\"description\"],\n                \"key_points\": [\"Performance\", \"Scalability\", \"Use case\"]\n            }\n            sources = [{\"type\": \"ADR\", \"id\": most_relevant_adr[\"id\"]}]\n        else:\n            direct_answer = {\n                \"summary\": \"No relevant ADR found\",\n                \"key_points\": []\n            }\n            sources = []\n    elif intent_type == \"CHANGE_IMPACT\":\n        direct_answer = {\n            \"summary\": \"Changing this code may break the functionality\",\n            \"key_points\": [\"Functionality\", \"Code\"]\n        }\n        sources = []\n    elif intent_type == \"HISTORICAL_QUERY\":\n        direct_answer = {\n            \"summary\": \"This code was implemented on a certain date\",\n            \"key_points\": [\"Date\", \"Code\"]\n        }\n        sources = []\n    else:\n        direct_answer = {\n            \"summary\": \"This is a code explanation question\",\n            \"key_points\": [\"Code\", \"Explanation\"]\n        }\n        sources = []\n\n    answer_template = {\n        \"question\": question,\n        \"intent_type\": intent_type,\n        \"confidence_score\": 0.9,\n        \"direct_answer\": direct_answer,\n        \"historical_context\": {},\n        \"technical_details\": {},\n        \"related_decisions\": [],\n        \"impact_of_changes\": {},\n        \"sources\": sources\n    }\n\n    return answer_template\n\nqa_function = {\n    \"name\": \"answerCodebaseQuestion\",\n    \"description\": \"Answers questions about the codebase\",\n    \"example_questions\": [\n        \"Why did we choose X?\",\n        \"What breaks if I change Y?\",\n        \"When was Z implemented?\"\n    ],\n    \"answer_template\": {\n        \"question\": \"\",\n        \"intent_type\": \"\",\n        \"confidence_score\": 0.0,\n        \"direct_answer\": {\n            \"summary\": \"\",\n            \"key_points\": []\n        },\n        \"historical_context\": {},\n        \"technical_details\": {},\n        \"related_decisions\": [],\n        \"impact_of_changes\": {},\n        \"sources\": []\n    }\n}\n\nsample_answers = [\n    {\n        \"question\": \"Why did we choose the main technology?\",\n        \"answer\": answer_codebase_question(\"Why did we choose the main technology?\")\n    },\n    {\n        \"question\": \"What breaks if I change the database?\",\n        \"answer\": answer_codebase_question(\"What breaks if I change the database?\")\n    },\n    {\n        \"question\": \"When was the authentication system implemented?\",\n        \"answer\": answer_codebase_question(\"When was the authentication system implemented?\")\n    }\n]\n\noutput = {\n    \"qa_function\": qa_function,\n    \"sample_answers\": sample_answers\n}\n\nprint(json.dumps(output, indent=2))\n",
  "",
  "",
  "json\n{\n  \"qa_function\": {\n    \"name\": \"answerCodebaseQuestion\",\n    \"description\": \"Answers questions about the codebase\",\n    \"example_questions\": [\n      \"Why did we choose X?\",\n      \"What breaks if I change Y?\",\n      \"When was Z implemented?\"\n    ],\n    \"answer_template\": {\n      \"question\": \"\",\n      \"intent_type\": \"\",\n      \"confidence_score\": 0.0,\n      \"direct_answer\": {\n        \"summary\": \"\",\n        \"key_points\": []\n      },\n      \"historical_context\": {},\n      \"technical_details\": {},\n      \"related_decisions\": [],\n      \"impact_of_changes\": {},\n      \"sources\": []\n    }\n  },\n  \"sample_answers\": [\n    {\n      \"question\": \"Why did we choose the main technology?\",\n      \"answer\": {\n        \"question\": \"Why did we choose the main technology?\",\n        \"intent_type\": \"DECISION_QUERY\",\n        \"confidence_score\": 0.9,\n        \"direct_answer\": {\n          \"summary\": \"This is the first ADR\",\n          \"key_points\": [\n            \"Performance\",\n            \"Scalability\",\n            \"Use case\"\n          ]\n        },\n        \"historical_context\": {},\n        \"technical_details\": {},\n        \"related_decisions\": [],\n        \"impact_of_changes\": {},\n        \"sources\": [\n          {\n            \"type\": \"ADR\",\n            \"id\": \"ADR-001\"\n          }\n        ]\n      }\n    },\n    {\n      \"question\": \"What breaks if I change the database?\",\n      \"answer\": {\n        \"question\": \"What breaks if I change the database?\",\n        \"intent_type\": \"CHANGE_IMPACT\",\n        \"confidence_score\": 0.9,\n        \"direct_answer\": {\n          \"summary\": \"Changing this code may break the functionality\",\n          \"key_points\": [\n            \"Functionality\",\n            \"Code\"\n          ]\n        },\n        \"historical_context\": {},\n        \"technical_details\": {},\n        \"related_decisions\": [],\n        \"impact_of_changes\": {},\n        \"sources\": []\n      }\n    },\n    {\n      \"question\": \"When was the authentication system implemented?\",\n      \"answer\": {\n        \"question\": \"When was the authentication system implemented?\",\n        \"intent_type\": \"HISTORICAL_QUERY\",\n        \"confidence_score\": 0.9,\n        \"direct_answer\": {\n          \"summary\": \"This code was implemented on a certain date\",\n          \"key_points\": [\n            \"Date\",\n            \"Code\"\n          ]\n        },\n        \"historical_context\": {},\n        \"technical_details\": {},\n        \"related_decisions\": [],\n        \"impact_of_changes\": {},\n        \"sources\": []\n      }\n    }\n  ]\n}\n",
  "",
  "",
  "python\nimport json\n\ndef answer_codebase_question(question):\n    analysis = {\n        \"total_decisions_found\": 2,\n        \"most_impactful_decision\": \"ADR-001\",\n        \"oldest_decision\": \"ADR-002\",\n        \"repositories_age_days\": 7,\n        \"complexity_score\": \"medium\"\n    }\n\n    adrs = [\n        {\"id\": \"ADR-001\", \"description\": \"This is the first ADR\"},\n        {\"id\": \"ADR-002\", \"description\": \"This is the second ADR\"}\n    ]\n\n    knowledge_graph = {\n        \"nodes\": 8,\n        \"edges\": []\n    }\n\n    if \"why\" in question.lower():\n        intent_type = \"DECISION_QUERY\"\n    elif \"what breaks\" in question.lower():\n        intent_type = \"CHANGE_IMPACT\"\n    elif \"when\" in question.lower():\n        intent_type = \"HISTORICAL_QUERY\"\n    else:\n        intent_type = \"CODE_EXPLANATION\"\n\n    if intent_type == \"DECISION_QUERY\":\n        most_relevant_adr = next((adr for adr in adrs if adr[\"id\"] == analysis[\"most_impactful_decision\"]), None)\n        if most_relevant_adr:\n            direct_answer = {\n                \"summary\": most_relevant_adr[\"description\"],\n                \"key_points\": [\"Performance\", \"Scalability\", \"Use case\"]\n            }\n            sources = [{\"type\": \"ADR\", \"id\": most_relevant_adr[\"id\"]}]\n        else:\n            direct_answer = {\n                \"summary\": \"No relevant ADR found\",\n                \"key_points\": []\n            }\n            sources = []\n    elif intent_type == \"CHANGE_IMPACT\":\n        direct_answer = {\n            \"summary\": \"Changing this code may break the functionality\",\n            \"key_points\": [\"Functionality\", \"Code\"]\n        }\n        sources = []\n    elif intent_type == \"HISTORICAL_QUERY\":\n        direct_answer = {\n            \"summary\": \"This code was implemented on a certain date\",\n            \"key_points\": [\"Date\", \"Code\"]\n        }\n        sources = []\n    else:\n        direct_answer = {\n            \"summary\": \"This is a code explanation question\",\n            \"key_points\": [\"Code\", \"Explanation\"]\n        }\n        sources = []\n\n    answer_template = {\n        \"question\": question,\n        \"intent_type\": intent_type,\n        \"confidence_score\": 0.9,\n        \"direct_answer\": direct_answer,\n        \"historical_context\": {},\n        \"technical_details\": {},\n        \"related_decisions\": [],\n        \"impact_of_changes\": {},\n        \"sources\": sources\n    }\n\n    return answer_template\n\nqa_function = {\n    \"name\": \"answerCodebaseQuestion\",\n    \"description\": \"Answers questions about the codebase\",\n    \"example_questions\": [\n        \"Why did we choose X?\",\n        \"What breaks if I change Y?\",\n        \"When was Z implemented?\"\n    ],\n    \"answer_template\": {\n        \"question\": \"\",\n        \"intent_type\": \"\",\n        \"confidence_score\": 0.0,\n        \"direct_answer\": {\n            \"summary\": \"\",\n            \"key_points\": []\n        },\n        \"historical_context\": {},\n        \"technical_details\": {},\n        \"related_decisions\": [],\n        \"impact_of_changes\": {},\n        \"sources\": []\n    }\n}\n\nsample_answers = [\n    {\n        \"question\": \"Why did we choose the main technology?\",\n        \"answer\": answer_codebase_question(\"Why did we choose the main technology?\")\n    },\n    {\n        \"question\": \"What breaks if I change the database?\",\n        \"answer\": answer_codebase_question(\"What breaks if I change the database?\")\n    },\n    {\n        \"question\": \"When was the authentication system implemented?\",\n        \"answer\": answer_codebase_question(\"When was the authentication system implemented?\")\n    }\n]\n\noutput = {\n    \"qa_function\": qa_function,\n    \"sample_answers\": sample_answers\n}\n\nprint(json.dumps(output, indent=2))\n",
  "",
  "",
  "json\n{\n  \"qa_function\": {\n    \"name\": \"answerCodebaseQuestion\",\n    \"description\": \"Answers questions about the codebase\",\n    \"example_questions\": [\n      \"Why did we choose X?\",\n      \"What breaks if I change Y?\",\n      \"When was Z implemented?\"\n    ],\n    \"answer_template\": {\n      \"question\": \"\",\n      \"intent_type\": \"\",\n      \"confidence_score\": 0.0,\n      \"direct_answer\": {\n        \"summary\": \"\",\n        \"key_points\": []\n      },\n      \"historical_context\": {},\n      \"technical_details\": {},\n      \"related_decisions\": [],\n      \"impact_of_changes\": {},\n      \"sources\": []\n    }\n  },\n  \"sample_answers\": [\n    {\n      \"question\": \"Why did we choose the main technology?\",\n      \"answer\": {\n        \"question\": \"Why did we choose the main technology?\",\n        \"intent_type\": \"DECISION_QUERY\",\n        \"confidence_score\": 0.9,\n        \"direct_answer\": {\n          \"summary\": \"This is the first ADR\",\n          \"key_points\": [\n            \"Performance\",\n            \"Scalability\",\n            \"Use case\"\n          ]\n        },\n        \"historical_context\": {},\n        \"technical_details\": {},\n        \"related_decisions\": [],\n        \"impact_of_changes\": {},\n        \"sources\": [\n          {\n            \"type\": \"ADR\",\n            \"id\": \"ADR-001\"\n          }\n        ]\n      }\n    },\n    {\n      \"question\": \"What breaks if I change the database?\",\n      \"answer\": {\n        \"question\": \"What breaks if I change the database?\",\n        \"intent_type\": \"CHANGE_IMPACT\",\n        \"confidence_score\": 0.9,\n        \"direct_answer\": {\n          \"summary\": \"Changing this code may break the functionality\",\n          \"key_points\": [\n            \"Functionality\",\n            \"Code\"\n          ]\n        },\n        \"historical_context\": {},\n        \"technical_details\": {},\n        \"related_decisions\": [],\n        \"impact_of_changes\": {},\n        \"sources\": []\n      }\n    },\n    {\n      \"question\": \"When was the authentication system implemented?\",\n      \"answer\": {\n        \"question\": \"When was the authentication system implemented?\",\n        \"intent_type\": \"HISTORICAL_QUERY\",\n        \"confidence_score\": 0.9,\n        \"direct_answer\": {\n          \"summary\": \"This code was implemented on a certain date\",\n          \"key_points\": [\n            \"Date\",\n            \"Code\"\n          ]\n        },\n        \"historical_context\": {},\n        \"technical_details\": {},\n        \"related_decisions\": [],\n        \"impact_of_changes\": {},\n        \"sources\": []\n      }\n    }\n  ]\n}\n",
  "",
  "",
  "python\nimport json\n\ndef answer_codebase_question(question):\n    analysis = {\n        \"total_decisions_found\": 2,\n        \"most_impactful_decision\": \"ADR-001\",\n        \"oldest_decision\": \"ADR-002\",\n        \"repositories_age_days\": 7,\n        \"complexity_score\": \"medium\"\n    }\n\n    adrs = [\n        {\"id\": \"ADR-001\", \"description\": \"This is the first ADR\"},\n        {\"id\": \"ADR-002\", \"description\": \"This is the second ADR\"}\n    ]\n\n    knowledge_graph = {\n        \"nodes\": 8,\n        \"edges\": []\n    }\n\n    if \"why\" in question.lower():\n        intent_type = \"DECISION_QUERY\"\n    elif \"what breaks\" in question.lower():\n        intent_type = \"CHANGE_IMPACT\"\n    elif \"when\" in question.lower():\n        intent_type = \"HISTORICAL_QUERY\"\n    else:\n        intent_type = \"CODE_EXPLANATION\"\n\n    if intent_type == \"DECISION_QUERY\":\n        most_relevant_adr = next((adr for adr in adrs if adr[\"id\"] == analysis[\"most_impactful_decision\"]), None)\n        if most_relevant_adr:\n            direct_answer = {\n                \"summary\": most_relevant_adr[\"description\"],\n                \"key_points\": [\"Performance\", \"Scalability\", \"Use case\"]\n            }\n            sources = [{\"type\": \"ADR\", \"id\": most_relevant_adr[\"id\"]}]\n        else:\n            direct_answer = {\n                \"summary\": \"No relevant ADR found\",\n                \"key_points\": []\n            }\n            sources = []\n    elif intent_type == \"CHANGE_IMPACT\":\n        direct_answer = {\n            \"summary\": \"Changing this code may break the functionality\",\n            \"key_points\": [\"Functionality\", \"Code\"]\n        }\n        sources = []\n    elif intent_type == \"HISTORICAL_QUERY\":\n        direct_answer = {\n            \"summary\": \"This code was implemented on a certain date\",\n            \"key_points\": [\"Date\", \"Code\"]\n        }\n        sources = []\n    else:\n        direct_answer = {\n            \"summary\": \"This is a code explanation question\",\n            \"key_points\": [\"Code\", \"Explanation\"]\n        }\n        sources = []\n\n    answer_template = {\n        \"question\": question,\n        \"intent_type\": intent_type,\n        \"confidence_score\": 0.9,\n        \"direct_answer\": direct_answer,\n        \"historical_context\": {},\n        \"technical_details\": {},\n        \"related_decisions\": [],\n        \"impact_of_changes\": {},\n        \"sources\": sources\n    }\n\n    return answer_template\n\nqa_function = {\n    \"name\": \"answerCodebaseQuestion\",\n    \"description\": \"Answers questions about the codebase\",\n    \"example_questions\": [\n        \"Why did we choose X?\",\n        \"What breaks if I change Y?\",\n        \"When was Z implemented?\"\n    ],\n    \"answer_template\": {\n        \"question\": \"\",\n        \"intent_type\": \"\",\n        \"confidence_score\": 0.0,\n        \"direct_answer\": {\n            \"summary\": \"\",\n            \"key_points\": []\n        },\n        \"historical_context\": {},\n        \"technical_details\": {},\n        \"related_decisions\": [],\n        \"impact_of_changes\": {},\n        \"sources\": []\n    }\n}\n\nsample_answers = [\n    {\n        \"question\": \"Why did we choose the main technology?\",\n        \"answer\": answer_codebase_question(\"Why did we choose the main technology?\")\n    },\n    {\n        \"question\": \"What breaks if I change the database?\",\n        \"answer\": answer_codebase_question(\"What breaks if I change the database?\")\n    },\n    {\n        \"question\": \"When was the authentication system implemented?\",\n        \"answer\": answer_codebase_question(\"When was the authentication system implemented?\")\n    }\n]\n\noutput = {\n    \"qa_function\": qa_function,\n    \"sample_answers\": sample_answers\n}\n\nprint(json.dumps(output, indent=2))\n",
  "",
  "",
  "json",
  {
    "qa_function": {
      "name": "answerCodebaseQuestion",
      "description": "Answers questions about the codebase",
      "example_questions": [
        "Why did we choose X?",
        "What breaks if I change Y?",
        "When was Z implemented?"
      ],
      "answer_template": {
        "question": "",
        "intent_type": "",
        "confidence_score": 0,
        "direct_answer": {
          "summary": "",
          "key_points": []
        },
        "historical_context": {},
        "technical_details": {},
        "related_decisions": [],
        "impact_of_changes": {},
        "sources": []
      }
    }
  }
]